[
  {
    "id": "20250820_162311",
    "timestamp": "2025-08-20T16:23:11.446505",
    "user_id": 636268954,
    "username": "pullerize",
    "name": "Сергей",
    "city": "Ташкент",
    "model": "фыв",
    "phone": "+998958485666"
  },
  {
    "id": "20250820_162841",
    "timestamp": "2025-08-20T16:28:41.437656",
    "user_id": 636268954,
    "username": "pullerize",
    "name": "sasas",
    "city": "sadasd",
    "model": "saas",
    "phone": "123123123123"
  },
  {
    "id": "20250820_163112",
    "timestamp": "2025-08-20T16:31:12.709102",
    "user_id": 636268954,
    "username": "pullerize",
    "name": "вфывы",
    "city": "фывфыв",
    "model": "фывфыв",
    "phone": "+998 90 998 99 99"
  },
  {
    "id": "20250820_165221",
    "timestamp": "2025-08-20T16:52:21.455309",
    "user_id": 636268954,
    "username": "pullerize",
    "name": "asdasd",
    "city": "asdasdas",
    "model": "asdasdasd",
    "phone": "+998 12 121 12 12"
  },
  {
    "id": "20250820_165551",
    "timestamp": "2025-08-20T16:55:51.966417",
    "user_id": 636268954,
    "username": "pullerize",
    "name": "Тест",
    "city": "Тестовый город",
    "model": "Тестовая марка",
    "phone": "+998 99 999 99 99"
  },
  {
    "id": "20250820_165939",
    "timestamp": "2025-08-20T16:59:39.916475",
    "user_id": 636268954,
    "username": "pullerize",
    "name": "Тест",
    "city": "Ташкент",
    "model": "Пр",
    "phone": "+998958485666"
  },
  {
    "id": "20250820_170030",
    "timestamp": "2025-08-20T17:00:30.336027",
    "user_id": 636268954,
    "username": "pullerize",
    "name": "Тестовое",
    "city": "фы",
    "model": "фы",
    "phone": "+998958485666"
  },
  {
    "id": "20250820_170109",
    "timestamp": "2025-08-20T17:01:09.559842",
    "user_id": 636268954,
    "username": "pullerize",
    "name": "фывфыв",
    "city": "фывфыв",
    "model": "фывфыв",
    "phone": "+998958485666"
  },
  {
    "id": "20250820_170252",
    "timestamp": "2025-08-20T17:02:52.345792",
    "user_id": 636268954,
    "username": "pullerize",
    "name": "вфывфы",
    "city": "фывфыв",
    "model": "фывфыв",
    "phone": "+998958485666"
  },
  {
    "id": "#1001",
    "timestamp": "2025-08-20T17:06:29.102155",
    "date": "20.08.2025 17:06",
    "user_id": 636268954,
    "username": "pullerize",
    "name": "Тестовое имя",
    "city": "Тестовый город",
    "model": "ыфвфыв",
    "phone": "+998958485666"
  },
  {
    "id": "#1002",
    "timestamp": "2025-08-20T17:13:04.851778",
    "date": "20.08.2025 17:13",
    "user_id": 636268954,
    "username": "pullerize",
    "name": "фывфывфы",
    "city": "фывфыв",
    "model": "вфыв",
    "phone": "+998 99 999 99 99"
  },
  {
    "id": "#1003",
    "timestamp": "2025-08-20T17:18:37.970015",
    "date": "20.08.2025 17:18",
    "user_id": 636268954,
    "username": "pullerize",
    "name": "фывфыв",
    "city": "фывфыв",
    "model": "фывфыв",
    "phone": "+998958485666"
  },
  {
    "id": "#1004",
    "timestamp": "2025-08-21T11:15:52.784123",
    "date": "21.08.2025 11:15",
    "user_id": 5887158228,
    "username": "Code_OneSix",
    "name": "умид талипов",
    "city": "Ташкент",
    "model": "444",
    "phone": "+79893537050"
  },
  {
    "id": "#1005",
    "timestamp": "2025-08-26T13:28:25.536001",
    "date": "26.08.2025 13:28",
    "user_id": 636268954,
    "username": "pullerize",
    "name": "Тест",
    "city": "Ташкент",
    "model": "Кат",
    "phone": "+998958485666"
  },
  {
    "id": "#1006",
    "timestamp": "2025-08-26T13:31:26.326218",
    "date": "26.08.2025 13:31",
    "user_id": 636268954,
    "username": "pullerize",
    "name": "Тест Тестович",
    "city": "Ташкент",
    "model": "Cat 444",
    "phone": "+998958485666"
  },
  {
    "id": "#1007",
    "timestamp": "2025-08-26T13:40:33.739732",
    "date": "26.08.2025 13:40",
    "user_id": 636268954,
    "username": "pullerize",
    "name": "Тест",
    "city": "Тафы",
    "model": "фы",
    "phone": "+998958485666"
  },
  {
    "id": "#1008",
    "timestamp": "2025-08-26T13:46:15.178266",
    "date": "26.08.2025 13:46",
    "user_id": 636268954,
    "username": "pullerize",
    "name": "Аавве",
    "city": "Уса",
    "model": "Вар",
    "phone": "+998958485666"
  },
  {
    "id": "#1009",
    "timestamp": "2025-08-26T13:55:25.936414",
    "date": "26.08.2025 13:55",
    "user_id": 6853255702,
    "username": "AnnaTsvetkovaZeppelin",
    "name": "Мари Ванна",
    "city": "Я с Венеры",
    "model": "Cat 434",
    "phone": "+998903705254"
  },
  {
    "id": "#1010",
    "timestamp": "2025-08-26T15:51:43.336058",
    "date": "26.08.2025 15:51",
    "user_id": 636268954,
    "username": "pullerize",
    "name": "тест",
    "city": "Ташкент",
    "model": "SEM655D",
    "phone": "+998958485666"
  },
  {
    "id": "#1011",
    "timestamp": "2025-08-26T15:52:54.588671",
    "date": "26.08.2025 15:52",
    "user_id": 636268954,
    "username": "pullerize",
    "name": "вфыфыв",
    "city": "фывфыв",
    "model": "фывфыв",
    "phone": "+998958485666"
  },
  {
    "id": "#1012",
    "timestamp": "2025-08-26T15:53:15.022801",
    "date": "26.08.2025 15:53",
    "user_id": 636268954,
    "username": "pullerize",
    "name": "фывфыв",
    "city": "фывфывфы",
    "model": "фывфыв",
    "phone": "+998958485666"
  },
  {
    "id": "#1013",
    "timestamp": "2025-08-26T15:57:43.816911",
    "date": "26.08.2025 15:57",
    "user_id": 636268954,
    "username": "pullerize",
    "name": "Тестовая",
    "city": "Тестовый город",
    "model": "Cat 444",
    "phone": "+998958485666"
  },
  {
    "id": "#1014",
    "timestamp": "2025-08-26T16:03:47.239800",
    "date": "26.08.2025 16:03",
    "user_id": 6853255702,
    "username": "AnnaTsvetkovaZeppelin",
    "name": "Мари Ванна",
    "city": "Ташкент",
    "model": "Cat 444",
    "phone": "+998903705254"
  },
  {
    "id": "#1015",
    "timestamp": "2025-08-26T16:05:23.479232",
    "date": "26.08.2025 16:05",
    "user_id": 636268954,
    "username": "pullerize",
    "name": "asdasda",
    "city": "asdasdas",
    "model": "asdasdasd",
    "phone": "+998958485666"
  },
  {
    "id": "#1016",
    "timestamp": "2025-08-26T16:07:54.097097",
    "date": "26.08.2025 16:07",
    "user_id": 636268954,
    "username": "pullerize",
    "name": "фывфыв",
    "city": "фывфывфыв",
    "model": "фывфывфыв",
    "phone": "+998958485666"
  },
  {
    "id": "#1017",
    "timestamp": "2025-08-26T16:08:48.529986",
    "date": "26.08.2025 16:08",
    "user_id": 636268954,
    "username": "pullerize",
    "name": "Сергей",
    "city": "Ташкент",
    "model": "SEM655",
    "phone": "+998958485666"
  },
  {
    "id": "#1018",
    "timestamp": "2025-08-26T16:10:32.742195",
    "date": "26.08.2025 16:10",
    "user_id": 636268954,
    "username": "pullerize",
    "name": "Сергей",
    "city": "Ташкент",
    "model": "фыфыыф",
    "phone": "+998958485666"
  },
  {
    "id": "#1019",
    "timestamp": "2025-08-26T16:11:49.508909",
    "date": "26.08.2025 16:11",
    "user_id": 6853255702,
    "username": "AnnaTsvetkovaZeppelin",
    "name": "Мари Ванна",
    "city": "Ташкент",
    "model": "Cat 444",
    "phone": "+998 90 370 52 54"
  },
  {
    "id": "#1020",
    "timestamp": "2025-08-26T16:27:48.812614",
    "date": "26.08.2025 16:27",
    "user_id": 6853255702,
    "username": "AnnaTsvetkovaZeppelin",
    "name": "Мари Ванна",
    "city": "Ташкент",
    "model": "cat 444",
    "phone": "+998903705254"
  },
  {
    "id": "#1021",
    "timestamp": "2025-08-26T16:28:41.335942",
    "date": "26.08.2025 16:28",
    "user_id": 6853255702,
    "username": "AnnaTsvetkovaZeppelin",
    "name": "Мари Ванна",
    "city": "Ташкент",
    "model": "Пппп",
    "phone": "+998 89 370 52 54"
  },
  {
    "id": "#1022",
    "timestamp": "2025-08-26T16:30:40.657925",
    "date": "26.08.2025 16:30",
    "user_id": 6853255702,
    "username": "AnnaTsvetkovaZeppelin",
    "name": "ророро",
    "city": "ророр",
    "model": "ллоло",
    "phone": "+998 90 999 99 99"
  },
  {
    "id": "#1023",
    "timestamp": "2025-08-26T17:02:43.871315",
    "date": "26.08.2025 17:02",
    "user_id": 6853255702,
    "username": "AnnaTsvetkovaZeppelin",
    "name": "ророр",
    "city": "лолол",
    "model": "лололо",
    "phone": "+998903705254"
  },
  {
    "id": "#1024",
    "timestamp": "2025-08-26T17:15:59.531005",
    "date": "26.08.2025 17:15",
    "user_id": 6853255702,
    "username": "AnnaTsvetkovaZeppelin",
    "name": "еппррп",
    "city": "рпрр",
    "model": "апапап",
    "phone": "+998903705254"
  }
]